revoice/__init__.py
revoice/revoice.py
revoice-3.0.1.dist-info/LICENSE
revoice-3.0.1.dist-info/METADATA
revoice-3.0.1.dist-info/WHEEL
revoice-3.0.1.dist-info/top_level.txt
revoice-3.0.1.dist-info/RECORD
