Metadata-Version: 2.1
Name: revoice
Version: 3.0.1
Summary: text to wav or speech.
Home-page: 
Author: ReBack
Author-email: 
Project-URL: Bug Tracker, https://github.com/pypa/sampleproject/issues
Keywords: voice
Classifier: Development Status :: 1 - Planning
Classifier: Intended Audience :: Developers
Classifier: Programming Language :: Python :: 3
Classifier: Operating System :: Unix
Classifier: Operating System :: MacOS :: MacOS X
Classifier: Operating System :: Microsoft :: Windows
License-File: LICENSE
Requires-Dist: httpx
Requires-Dist: uuid
